minerva_tech_theme/__init__.py
minerva_tech_theme/_version.py
minerva_tech_theme-0.1.0.data/data/share/jupyter/labextensions/minerva-tech-theme/build_log.json
minerva_tech_theme-0.1.0.data/data/share/jupyter/labextensions/minerva-tech-theme/package.json
minerva_tech_theme-0.1.0.data/data/share/jupyter/labextensions/minerva-tech-theme/static/lib_index_js.e09beb7a7b1046812238.js
minerva_tech_theme-0.1.0.data/data/share/jupyter/labextensions/minerva-tech-theme/static/lib_index_js.e09beb7a7b1046812238.js.map
minerva_tech_theme-0.1.0.data/data/share/jupyter/labextensions/minerva-tech-theme/static/remoteEntry.00d6f038e609b952b7c1.js
minerva_tech_theme-0.1.0.data/data/share/jupyter/labextensions/minerva-tech-theme/static/remoteEntry.00d6f038e609b952b7c1.js.map
minerva_tech_theme-0.1.0.data/data/share/jupyter/labextensions/minerva-tech-theme/static/style.js
minerva_tech_theme-0.1.0.data/data/share/jupyter/labextensions/minerva-tech-theme/themes/minerva-tech-theme/index.css
minerva_tech_theme-0.1.0.data/data/share/jupyter/labextensions/minerva-tech-theme/themes/minerva-tech-theme/index.js
minerva_tech_theme-0.1.0.data/data/share/jupyter/labextensions/minerva-tech-theme/install.json
minerva_tech_theme-0.1.0.dist-info/METADATA
minerva_tech_theme-0.1.0.dist-info/WHEEL
minerva_tech_theme-0.1.0.dist-info/licenses/LICENSE
minerva_tech_theme-0.1.0.dist-info/RECORD
