Metadata-Version: 2.3
Name: minerva_tech_theme
Version: 0.1.0
Dynamic: Keywords
Summary: A JupyterLab Theme for the MinervaTechnologies.
Project-URL: Homepage, https://github.com/Minerva-Technologies/minerva-jupyterlab-theme.git
Project-URL: Bug Tracker, https://github.com/Minerva-Technologies/minerva-jupyterlab-theme.git/issues
Project-URL: Repository, https://github.com/Minerva-Technologies/minerva-jupyterlab-theme.git.git
Author-email: Saman <samanf74@gmail.com>
License: BSD 3-Clause License
License-File: LICENSE
Classifier: Framework :: Jupyter
Classifier: Framework :: Jupyter :: JupyterLab
Classifier: Framework :: Jupyter :: JupyterLab :: 4
Classifier: Framework :: Jupyter :: JupyterLab :: Extensions
Classifier: Framework :: Jupyter :: JupyterLab :: Extensions :: Prebuilt
Classifier: License :: OSI Approved :: BSD License
Classifier: Programming Language :: Python
Classifier: Programming Language :: Python :: 3
Classifier: Programming Language :: Python :: 3.8
Classifier: Programming Language :: Python :: 3.9
Classifier: Programming Language :: Python :: 3.10
Classifier: Programming Language :: Python :: 3.11
Classifier: Programming Language :: Python :: 3.12
Requires-Python: >=3.8
